Workbook

Sheet TrustLayerAI
A1: 2A202600405 - Nguyễn Thị Ngọc
A2: Product: TrustLayerAI - Đánh giá RAG/Enterprise Search (chatbot nội bộ)
B3: Ex: Vingroup Ecosystem -
B4: Số lượng chatbot nội bộ: 1 chatbot
B5: Tần suất sử dụng trung bình: Khoảng 20 lần/tuần cho mỗi nhân viên.
B6: Nếu có 1.000 nhân viên, lượng request hàng tháng có thể đạt khoảng:
B7: 1.000 nhân viên * 20 requests/ tuần * 4 tuần = 80.000 requests
B9: Giả định token / request
B10: Input: 1,000 tokens/request , đơn giá $0.25$/1M tokens
B11: Output: 500 tokens/request , đơn giá 2$ / 1M tokens
B12: Tổng input tokens: 80.000 * 1000 = 80.000.000
B13: Tổng output tokens: 80.000 * 500 = 40.000.000
B14: Tổng tokens: 120.000.000
B15: 4. Tính cost (GPT-5 mini)
... B20: Tổng API Cost: $100 / tháng = 2.550.000 vnd

Sheet 1. Assumptions
B2: Tab 1 — ASSUMPTIONS / Giả định đầu vào
B3: Luật chơi: chỉ điền vào các ô MÀU VÀNG. Các ô khác là công thức và sẽ tự tính.
B5: 1. Product & Pricing / Sản phẩm & Giá
C6: Optimistic | D6: Base | E6: Pessimistic | F6: Đơn vị | G6: Ghi chú / Note
B7: ARPU — Giá bán bình quân/khách/tháng | C7: 50000000 | D7: 20400000 | E7: 2000000 | F7: VND | G7: Pricing cao hơn → khó bán hơn nhưng margin tốt hơn | H7: Willing to pay của khách hàng như thế nào? => Willing to pay của ARPU =? Customers: B2B | I7: GPT-5 mini optimized: $5–15 / khách / tháng Bao nhiêu khách hàng / tháng: 2 khách hàng Tần xuất sử dụng feature: 1 tuần / 1 lần (thường cuối tuần để review & làm report) Mỗi user trong 1 tháng, trung bình họ phát sinh bao nhiêu transaction, để xem họ trả mình bao nhiêu tiền ? Tính bao nhiêu token/ turn ( gồm cả input & output )
B8: Adoption rate — % TAM chuyển thành khách/tháng | C8: 0.012 | D8: 0.006 | E8: 0.002 | F8: %/tháng | G8: % TAM chuyển thành khách trả tiền mới mỗi tháng
B9: Total addressable market (số khách tiềm năng) | C9: 50000 | D9: 5 | E9: 50000 | F9: khách | G9: Tổng số khách hàng tiềm năng có thể tiếp cận được
B11: 2. COGS / Chi phí biến đổi trên mỗi khách hàng
B12: API cost / khách / tháng | C12: 1000000 | D12: 2550000 | E12: 10000000 | F12: VND | G12: Tiền gọi OpenAI/Anthropic/Gemini API | H12: 1000 requests/ tháng cho 100 sp AI => Usage × Token × Price
B13: Hidden costs (labeling, retraining, QA) | C13: 30000 | D13: 3000000 | E13: 10000000 | F13: VND | G13: Đừng quên! Đây là cục giết startup AI
B14: Infrastructure (server/cloud) / khách | C14: 20000 | D14: 2000000 | E14: 5000000 | F14: VND | G14: Phần allocate cloud cost cho mỗi khách
B15: → Tổng COGS / khách / tháng | C15: =C12+C13+C14 -> 1050000 | D15: =D12+D13+D14 -> 7550000 | E15: =E12+E13+E14 -> 25000000
B17: 3. Customer Behavior / Hành vi khách hàng
B18: Monthly Churn Rate — % khách rời mỗi tháng | C18: 0.01 | D18: 0.03 | E18: 0.08 | F18: % | G18: Benchmark AI product < 5%/tháng
B19: → Số tháng ở lại trung bình | C19: =IFERROR(1/C18,0) -> 100 | D19: =IFERROR(1/D18,0) -> 33.333333 | E19: =IFERROR(1/E18,0) -> 12.5
B21: 4. Sales & Marketing / Chi phí thu hút khách
B22: CAC — Tổng chi phí có 1 khách hàng mới | C22: 800000 | D22: 50000000 | E22: 10000000 | F22: VND | G22: Tổng tiền Marketing & Sales / Số khách mới
B24: 5. Fixed Costs / Chi phí cố định hàng tháng
B25: Salaries — Lương team (PM/Dev/Designer) | C25: 80000000 | D25: 200000000 | E25: 500000000 | F25: VND/tháng | G25: Pessimistic = phải hire thêm nếu khó scale
B26: Office, tools, admin | C26: 15000000 | D26: 100000000 | E26: 25000000 | F26: VND/tháng
B27: Marketing budget hàng tháng | C27: 50000000 | D27: 200000000 | E27: 500000000 | F27: VND/tháng
B28: → Tổng Fixed Cost / tháng | C28: =SUM(C25:C27) -> 145000000 | D28: =SUM(D25:D27) -> 500000000 | E28: =SUM(E25:E27) -> 1025000000
B30: 6. Initial Investment / Vốn đầu tư ban đầu
B31: Vốn đầu tư ban đầu (build MVP, setup) | C31: 100000000 | D31: 500000000 | E31: 1000000000 | F31: VND | G31: Chi phí 1 lần — lương team build MVP, infrastructure setup
B32: Tiền mặt ban đầu (sau khi đã trừ vốn đầu tư) | C32: 2000000000 | D32: 3000000000 | E32: 5000000000 | F32: VND | G32: Số tiền có sẵn để chi trả fixed cost trong giai đoạn đầu
B34: 7. Discount Rate / Tỷ suất chiết khấu (cho NPV)
B35: Annual discount rate (WACC) | C35: 0.2 | D35: 0.2 | E35: 0.2 | F35: %/năm | G35: Mức kỳ vọng tối thiểu của nhà đầu tư cho dự án AI rủi ro
B36: → Monthly discount rate | C36: =(1+C35)^(1/12)-1 -> 0.01530947 | D36: =(1+D35)^(1/12)-1 -> 0.01530947 | E36: =(1+E35)^(1/12)-1 -> 0.01530947
B38: 8. Decision Note / Ghi chú quyết định
B39: Tại sao bạn chọn mức ARPU và CAC như trên? Logic gì để bảo vệ những con số này trước nhà đầu tư? Viết 2-3 câu… 1. Chọn mức ARPU = 20.400.000 vì dựa vào ngưỡng Willing to pay của khách hàng. Ngưỡng Willing To Pay = 5%-30% * ( Expected Risk) Expected Risk=Volume×Critical Rate×Error Rate×Cost per Error Volume = số AI requests Critical Rate = % request quan trọng Error Rate = % sai Cost/Error = thiệt hại mỗi lỗi WTP = 10% * (80,000 requests/ngày * 1% critical * 2% error * 500$) = 8000$ /thang = 204.000.000 2. Tunning Ban đầu: - ARPU: 20.4M - COGS: 0.4335M → Gross margin = 78.8% (vượt ngưỡng) - Churn 5% → Lifetime ≈ 20 tháng - LTV/ CAC Ratio 10.71x ( rất mạnh, nên được điều chỉnh để phản ánh thực tế) - Payback period 1.9 tháng ( rất nhanh, nên được điều chỉnh để phản ánh thực tế) Điều chỉnh: - Điều chỉnh COGS ~ 7M -> Gross margin = 63% ( bao gồm hạ tầng và vận hành) - Điều chỉnh churn cho thực tế hơn vì 5%/tháng hơi cao so với enterprise. => 3%/tháng phản ánh mức gắn bó cao hơn của khách hàng enterprise - Tăng CAC =50M bao gồm chi phí pre-sales, POC và triển khai => LTV / CAC Ratio = 8.57% (rất mạnh, tối ưu, được điều chỉnh thực tế hơn) - Playback period 3.9 tháng (hợp lí hơn)
G41: 3. Logic bảo vệ những con số: - ARPU được xác định dựa trên value-based pricing, theo ngưỡng willingness to pay của khách hàng, tương đương khoảng 5–20% giá trị rủi ro mà hệ thống giúp giảm thiểu trong vận hành AI. Với quy mô sử dụng thực tế, mức giá 20.4 triệu/tháng phản ánh đúng giá trị mang lại thay vì chi phí API. - CAC được điều chỉnh lên khoảng 50 triệu để phản ánh chu kỳ bán hàng enterprise (pre-sales, POC, integration), đồng thời giữ LTV/CAC ở mức hấp dẫn và thực tế khi mở rộng. - Các giả định ban đầu cho thấy unit economics rất mạnh với biên lợi nhuận cao và thời gian hoàn vốn nhanh. Tuy nhiên, để phản ánh sát hơn thực tế triển khai enterprise, các tham số đã được điều chỉnh theo hướng thận trọng hơn, bao gồm tăng COGS, giảm churn và tăng CAC. Sau điều chỉnh, mô hình vẫn duy trì LTV/CAC ~8.6x và payback ~4 tháng, cho thấy hiệu quả kinh tế hấp dẫn nhưng đáng tin cậy khi mở rộng.

Sheet 2. Unit Economics
B2: Tab 2 — UNIT ECONOMICS / Kinh tế đơn vị
B3: Tự động tính từ Tab 1. Kiểm tra: LTV/CAC > 3 (Base) và CAC Payback < 12 tháng.
B5: Chỉ số | C5: Optimistic | D5: Base | E5: Pessimistic | F5: Đơn vị | G5: Benchmark / Note
B7: Trên mỗi khách hàng / per customer
B8: ARPU / tháng | C8: ='1. Assumptions'!C7 -> 50000000 | D8: ='1. Assumptions'!D7 -> 20400000 | E8: ='1. Assumptions'!E7 -> 2000000 | F8: VND | G8: Liên kết từ Tab Assumptions
B9: COGS / tháng | C9: ='1. Assumptions'!C15 -> 1050000 | D9: ='1. Assumptions'!D15 -> 7550000 | E9: ='1. Assumptions'!E15 -> 25000000 | F9: VND
B10: → Gross Profit / tháng | C10: =C8-C9 -> 48950000 | D10: =D8-D9 -> 12850000 | E10: =E8-E9 -> -23000000
B11: → Gross Margin % | C11: =IFERROR(C10/C8,0) -> 0.979 | D11: =IFERROR(D10/D8,0) -> 0.62990196 | E11: =IFERROR(E10/E8,0) -> -11.5 | G11: AI product target: 40-60%. SaaS truyền thống: 80%+
B13: LTV — Customer Lifetime Value
B14: Số tháng ở lại trung bình | C14: ='1. Assumptions'!C19 -> 100 | D14: ='1. Assumptions'!D19 -> 33.333333 | E14: ='1. Assumptions'!E19 -> 12.5 | F14: tháng
B15: → LTV = Gross Profit × Số tháng ở lại | C15: =C10*C14 -> 4895000000 | D15: =D10*D14 -> 4.2833333e+08 | E15: =E10*E14 -> -287500000 | G15: Tổng lợi nhuận gộp một khách mang lại trong vòng đời
B17: CAC — Customer Acquisition Cost
B18: CAC — Chi phí thu hút 1 khách | C18: ='1. Assumptions'!C22 -> 800000 | D18: ='1. Assumptions'!D22 -> 50000000 | E18: ='1. Assumptions'!E22 -> 10000000 | F18: VND
B20: Key Ratios / Tỷ lệ then chốt
B21: → LTV / CAC Ratio | C21: =IFERROR(C15/C18,0) -> 6118.75 | D21: =IFERROR(D15/D18,0) -> 8.5666667 | E21: =IFERROR(E15/E18,0) -> -28.75 | G21: 🎯 Target > 3.0x (tiêu chuẩn vàng VC)
B22: → CAC Payback Period | C22: =IFERROR(C18/C10,0) -> 0.016343207 | D22: =IFERROR(D18/D10,0) -> 3.8910506 | E22: =IFERROR(E18/E10,0) -> -0.43478261 | G22: 🎯 Target < 12 tháng (early-stage)
B24: Verdict / Kết luận
B25: Unit Economics Status | C25: =IF(AND(C21>=3,C22<=12),"✓ HEALTHY",IF(OR(C21<1,C22>18),"✗ UNHEALTHY","⚠ WATCH")) -> ✓ HEALTHY | D25: =IF(AND(D21>=3,D22<=12),"✓ HEALTHY",IF(OR(D21<1,D22>18),"✗ UNHEALTHY","⚠ WATCH")) -> ✓ HEALTHY | E25: =IF(AND(E21>=3,E22<=12),"✓ HEALTHY",IF(OR(E21<1,E22>18),"✗ UNHEALTHY","⚠ WATCH")) -> ✗ UNHEALTHY

Sheet 3. P&L & ROI
B2: Tab 3 — P&L & ROI / 24 tháng
B4: Chọn scenario: | C4: Base | D4: Đổi scenario tại đây để toàn bộ P&L tự cập nhật
B6: Active scenario index: | C6: =MATCH(C4,{"Optimistic","Base","Pessimistic"},0) -> 2
B7: Selected scenario inputs ↓
B8: ARPU / khách / tháng | C8: =CHOOSE($C$6,'1. Assumptions'!C7,'1. Assumptions'!D7,'1. Assumptions'!E7) -> 20400000
B9: Adoption rate | C9: =CHOOSE($C$6,'1. Assumptions'!C8,'1. Assumptions'!D8,'1. Assumptions'!E8) -> 0.006
B10: TAM (số khách tiềm năng) | C10: =CHOOSE($C$6,'1. Assumptions'!C9,'1. Assumptions'!D9,'1. Assumptions'!E9) -> 5
B11: Total COGS / khách | C11: =CHOOSE($C$6,'1. Assumptions'!C15,'1. Assumptions'!D15,'1. Assumptions'!E15) -> 7550000
B12: Monthly Churn Rate | C12: =CHOOSE($C$6,'1. Assumptions'!C18,'1. Assumptions'!D18,'1. Assumptions'!E18) -> 0.03
B13: CAC / khách mới | C13: =CHOOSE($C$6,'1. Assumptions'!C22,'1. Assumptions'!D22,'1. Assumptions'!E22) -> 50000000
B14: Fixed Cost / tháng | C14: =CHOOSE($C$6,'1. Assumptions'!C28,'1. Assumptions'!D28,'1. Assumptions'!E28) -> 500000000
B15: Initial Investment | C15: =CHOOSE($C$6,'1. Assumptions'!C31,'1. Assumptions'!D31,'1. Assumptions'!E31) -> 500000000
B16: Initial Cash | C16: =CHOOSE($C$6,'1. Assumptions'!C32,'1. Assumptions'!D32,'1. Assumptions'!E32) -> 3000000000
B17: Monthly Discount Rate | C17: =CHOOSE($C$6,'1. Assumptions'!C36,'1. Assumptions'!D36,'1. Assumptions'!E36) -> 0.01530947
B20: P&L Projection — 24 months (VND)
B21: Month | C21: M1 | D21: M2 | E21: M3 | F21: M4 | G21: M5 | H21: M6 | I21: M7 | J21: M8 | K21: M9 | L21: M10 | M21: M11 | N21: M12 | O21: M13 | P21: M14 | Q21: M15 | R21: M16 | S21: M17 | T21: M18 | U21: M19 | V21: M20 | W21: M21 | X21: M22 | Y21: M23 | Z21: M24 | AA21: TOTAL
B22: New customers acquired | C22: =ROUND($C$10*$C$9,0) -> 0 | D22: =ROUND($C$10*$C$9,0) -> 0 | E22: =ROUND($C$10*$C$9,0) -> 0 | F22: =ROUND($C$10*$C$9,0) -> 0 | G22: =ROUND($C$10*$C$9,0) -> 0 | H22: =ROUND($C$10*$C$9,0) -> 0 | I22: =ROUND($C$10*$C$9,0) -> 0 | J22: =ROUND($C$10*$C$9,0) -> 0 | ... Z22: =ROUND($C$10*$C$9,0) -> 0 | AA22: =SUM(C22:Z22) -> 0
B23: Active customers (end of month) | C23: =C22 -> 0 | D23: =C23*(1-$C$12)+D22 -> 0 | E23: =D23*(1-$C$12)+E22 -> 0 | F23: =E23*(1-$C$12)+F22 -> 0 | G23: =F23*(1-$C$12)+G22 -> 0 | H23: =G23*(1-$C$12)+H22 -> 0 | I23: =H23*(1-$C$12)+I22 -> 0 | J23: =I23*(1-$C$12)+J22 -> 0 | K23: =J23*(1-$C$12)+K22 -> 0 | ... Z23: =Y23*(1-$C$12)+Z22 -> 0
B25: Revenue | C25: =C23*$C$8 -> 0 | D25: =D23*$C$8 -> 0 | E25: =E23*$C$8 -> 0 | F25: =F23*$C$8 -> 0 | G25: =G23*$C$8 -> 0 | H25: =H23*$C$8 -> 0 | I25: =I23*$C$8 -> 0 | J25: =J23*$C$8 -> 0 | ... Z25: =Z23*$C$8 -> 0 | AA25: =SUM(C25:Z25) -> 0
B26: COGS (variable cost) | C26: =C23*$C$11 -> 0 | D26: =D23*$C$11 -> 0 | E26: =E23*$C$11 -> 0 | F26: =F23*$C$11 -> 0 | G26: =G23*$C$11 -> 0 | H26: =H23*$C$11 -> 0 | I26: =I23*$C$11 -> 0 | J26: =J23*$C$11 -> 0 | ... Z26: =Z23*$C$11 -> 0 | AA26: =SUM(C26:Z26) -> 0
B27: Gross Profit | C27: =C25-C26 -> 0 | D27: =D25-D26 -> 0 | E27: =E25-E26 -> 0 | F27: =F25-F26 -> 0 | G27: =G25-G26 -> 0 | H27: =H25-H26 -> 0 | I27: =I25-I26 -> 0 | J27: =J25-J26 -> 0 | ... Z27: =Z25-Z26 -> 0 | AA27: =SUM(C27:Z27) -> 0
B28: Marketing/Acquisition cost | C28: =C22*$C$13 -> 0 | D28: =D22*$C$13 -> 0 | E28: =E22*$C$13 -> 0 | F28: =F22*$C$13 -> 0 | G28: =G22*$C$13 -> 0 | H28: =H22*$C$13 -> 0 | I28: =I22*$C$13 -> 0 | J28: =J22*$C$13 -> 0 | ... Z28: =Z22*$C$13 -> 0 | AA28: =SUM(C28:Z28) -> 0
B29: Fixed cost (salaries + ops) | C29: =$C$14 -> 500000000 | D29: =$C$14 -> 500000000 | E29: =$C$14 -> 500000000 | F29: =$C$14 -> 500000000 | G29: =$C$14 -> 500000000 | H29: =$C$14 -> 500000000 | I29: =$C$14 -> 500000000 | J29: =$C$14 -> 500000000 | ... Z29: =$C$14 -> 500000000 | AA29: =SUM(C29:Z29) -> 12000000000
B30: Operating Profit (EBITDA) | C30: =C27-C28-C29 -> -500000000 | D30: =D27-D28-D29 -> -500000000 | E30: =E27-E28-E29 -> -500000000 | F30: =F27-F28-F29 -> -500000000 | G30: =G27-G28-G29 -> -500000000 | H30: =H27-H28-H29 -> -500000000 | I30: =I27-I28-I29 -> -500000000 | J30: =J27-J28-J29 -> -500000000 | ... Z30: =Z27-Z28-Z29 -> -500000000 | AA30: =SUM(C30:Z30) -> -12000000000
B32: Cash Flow (after investment) | C32: =C30-$C$15 -> -1000000000 | D32: =D30 -> -500000000 | E32: =E30 -> -500000000 | F32: =F30 -> -500000000 | G32: =G30 -> -500000000 | H32: =H30 -> -500000000 | I32: =I30 -> -500000000 | J32: =J30 -> -500000000 | K32: =K30 -> -500000000 | ... Z32: =Z30 -> -500000000 | AA32: =SUM(C32:Z32) -> -12500000000
B33: Cash Position (cumulative) | C33: =$C$16+C32 -> 2000000000 | D33: =C33+D32 -> 1500000000 | E33: =D33+E32 -> 1000000000 | F33: =E33+F32 -> 500000000 | G33: =F33+G32 -> 0 | H33: =G33+H32 -> -500000000 | I33: =H33+I32 -> -1000000000 | J33: =I33+J32 -> -1500000000 | K33: =J33+K32 -> -2000000000 | ... Z33: =Y33+Z32 -> -9500000000
B36: ROI Metrics / Chỉ số đánh giá tổng thể dự án
B37: NPV (Net Present Value, mil VND) | C37: =(NPV($C$17,D32:Z32)+C32)/1000000 -> -10632.076 | D37: ="(target: > 0)" -> (target: > 0)
B38: IRR (Annual) | C38: =IFERROR((1+IRR(C32:Z32))^12-1,0) -> 0 | D38: ="(target: > "&TEXT(CHOOSE($C$6,'1. Assumptions'!C35,'1. Assumptions'!D35,'1. Assumptions'!E35),"0.0%")&")" -> (target: > 20.0%)
B39: Project Payback (months) | C39: =IFERROR(MATCH(TRUE(),INDEX(C41:Z41>=0,0),0),"> 24") -> > 24 | D39: ="(target: < 24)" -> (target: < 24)
B40: Runway (months until cash = 0) | C40: =IFERROR(MATCH(TRUE(),INDEX(C33:Z33<0,0),0)-1,">= 24") -> 5 | D40: ="(target: >= 12)" -> (target: >= 12)
B41: (helper: cumulative cash flow) | C41: =C32 -> -1000000000 | D41: =C41+D32 -> -1500000000 | E41: =D41+E32 -> -2000000000 | F41: =E41+F32 -> -2500000000 | G41: =F41+G32 -> -3000000000 | H41: =G41+H32 -> -3500000000 | I41: =H41+I32 -> -4000000000 | J41: =I41+J32 -> -4500000000 | K41: =J41+K32 -> -5000000000 | ... Z41: =Y41+Z32 -> -12500000000
B43: Final Verdict / Có nên làm dự án này?
B44: Project Decision | C44: =IF(AND(C37>0,C38>CHOOSE($C$6,'1. Assumptions'!C35,'1. Assumptions'!D35,'1. Assumptions'!E35)),"✓ GO — NPV+ và IRR > WACC",IF(C37<0,"✗ NO-GO — NPV âm: dự án không tạo giá trị","⚠ HOLD — IRR thấp hơn kỳ vọng, cần điều chỉnh")) -> ✗ NO-GO — NPV âm: dự án không tạo giá trị
